shgo/__init__.py
shgo/_shgo.py
shgo/_tgo.py
shgo/_shgo_lib/__init__.py
shgo/_shgo_lib/_complex.py
shgo/_shgo_lib/_field.py
shgo/_shgo_lib/_misc.py
shgo/_shgo_lib/_plotting.py
shgo/_shgo_lib/_vertex.py
shgo/_shgo_lib/_vertex_group.py
shgo/_shgo_lib/sobol_seq.py
shgo/_shgo_lib/sobol_vec.gz
shgo/_shgo_lib/triangulation.py
shgo/shgo_m/__init__.py
shgo/shgo_m/sobol_seq.py
shgo/shgo_m/sobol_vec.gz
shgo/shgo_m/triangulation.py
shgo/tests/__init__.py
shgo/tests/test__shgo.py
shgo-1.0.0.dist-info/LICENSE
shgo-1.0.0.dist-info/METADATA
shgo-1.0.0.dist-info/WHEEL
shgo-1.0.0.dist-info/top_level.txt
shgo-1.0.0.dist-info/RECORD
