Metadata-Version: 2.1
Name: shgo
Version: 1.0.0
Summary: Simplicial homology global optimisation
Home-page: https://github.com/stefan-endres/shgo
Author: Stefan Endres, Carl Sandrock
Author-email: stefan.c.endres@gmail.com
License: MIT
Keywords: optimization
Classifier: Development Status :: 5 - Production/Stable
Classifier: Intended Audience :: Science/Research
Classifier: Intended Audience :: Developers
Classifier: Topic :: Scientific/Engineering
Classifier: Topic :: Scientific/Engineering :: Mathematics
Classifier: License :: OSI Approved :: MIT License
Classifier: Programming Language :: Python :: 3
License-File: LICENSE
Requires-Dist: scipy
Requires-Dist: numpy
Requires-Dist: pytest
Requires-Dist: pytest-cov
